rsd_lib/__init__.py
rsd_lib/base.py
rsd_lib/common.py
rsd_lib/constants.py
rsd_lib/exceptions.py
rsd_lib/main.py
rsd_lib/utils.py
rsd_lib/resources/__init__.py
rsd_lib/resources/v2_1/__init__.py
rsd_lib/resources/v2_1/types.py
rsd_lib/resources/v2_1/chassis/__init__.py
rsd_lib/resources/v2_1/chassis/chassis.py
rsd_lib/resources/v2_1/chassis/log_entry.py
rsd_lib/resources/v2_1/chassis/log_service.py
rsd_lib/resources/v2_1/chassis/power.py
rsd_lib/resources/v2_1/chassis/power_zone.py
rsd_lib/resources/v2_1/chassis/thermal.py
rsd_lib/resources/v2_1/chassis/thermal_zone.py
rsd_lib/resources/v2_1/common/__init__.py
rsd_lib/resources/v2_1/common/ip_addresses.py
rsd_lib/resources/v2_1/common/message.py
rsd_lib/resources/v2_1/common/rack_location.py
rsd_lib/resources/v2_1/common/redundancy.py
rsd_lib/resources/v2_1/ethernet_switch/__init__.py
rsd_lib/resources/v2_1/ethernet_switch/ethernet_switch.py
rsd_lib/resources/v2_1/ethernet_switch/ethernet_switch_acl.py
rsd_lib/resources/v2_1/ethernet_switch/ethernet_switch_acl_rule.py
rsd_lib/resources/v2_1/ethernet_switch/ethernet_switch_port.py
rsd_lib/resources/v2_1/ethernet_switch/ethernet_switch_static_mac.py
rsd_lib/resources/v2_1/ethernet_switch/schemas.py
rsd_lib/resources/v2_1/ethernet_switch/vlan_network_interface.py
rsd_lib/resources/v2_1/event_service/__init__.py
rsd_lib/resources/v2_1/event_service/event_destination.py
rsd_lib/resources/v2_1/event_service/event_service.py
rsd_lib/resources/v2_1/event_service/schemas.py
rsd_lib/resources/v2_1/fabric/__init__.py
rsd_lib/resources/v2_1/fabric/endpoint.py
rsd_lib/resources/v2_1/fabric/fabric.py
rsd_lib/resources/v2_1/fabric/port.py
rsd_lib/resources/v2_1/fabric/switch.py
rsd_lib/resources/v2_1/fabric/zone.py
rsd_lib/resources/v2_1/manager/__init__.py
rsd_lib/resources/v2_1/manager/manager.py
rsd_lib/resources/v2_1/manager/manager_network_protocol.py
rsd_lib/resources/v2_1/manager/serial_interface.py
rsd_lib/resources/v2_1/manager/virtual_media.py
rsd_lib-1.2.0.dist-info/AUTHORS
rsd_lib-1.2.0.dist-info/LICENSE
rsd_lib-1.2.0.dist-info/METADATA
rsd_lib-1.2.0.dist-info/WHEEL
rsd_lib-1.2.0.dist-info/pbr.json
rsd_lib-1.2.0.dist-info/top_level.txt
rsd_lib-1.2.0.dist-info/RECORD
