Metadata-Version: 2.1
Name: rsd-lib
Version: 1.2.0
Summary: Extended Sushy library for Rack Scale Design
Home-page: https://opendev.org/x/rsd-lib
Author: OpenStack
Author-email: openstack-discuss@lists.openstack.org
License: UNKNOWN
Platform: UNKNOWN
Classifier: Environment :: OpenStack
Classifier: Intended Audience :: Information Technology
Classifier: Intended Audience :: System Administrators
Classifier: License :: OSI Approved :: Apache Software License
Classifier: Operating System :: POSIX :: Linux
Classifier: Programming Language :: Python
Classifier: Programming Language :: Python :: 2
Classifier: Programming Language :: Python :: 2.7
Classifier: Programming Language :: Python :: 3
Classifier: Programming Language :: Python :: 3.5
Classifier: Programming Language :: Python :: 3.6
Requires-Dist: pbr (>=2.0)
Requires-Dist: sushy (>=2.0.0)
Requires-Dist: jsonschema (>=2.6.0)
